backendcrew/__init__.py
backendcrew/check_tools.py
backendcrew/conditions.py
backendcrew/crew.py
backendcrew/database.py
backendcrew/flow.py
backendcrew/llm_config.py
backendcrew/memory_config.py
backendcrew/models.py
backendcrew/server.py
backendcrew/test_logs.py
backendcrew/uc_client.py
backendcrew/api/__init__.py
backendcrew/api/agents.py
backendcrew/api/crew_store.py
backendcrew/api/databricks.py
backendcrew/api/flow_store.py
backendcrew/api/generate_agent.py
backendcrew/api/generate_connections.py
backendcrew/api/generate_crew.py
backendcrew/api/generate_job_name.py
backendcrew/api/generate_task.py
backendcrew/api/generate_templates.py
backendcrew/api/job_output_streaming.py
backendcrew/api/jobs.py
backendcrew/api/keys.py
backendcrew/api/logs.py
backendcrew/api/memory.py
backendcrew/api/recipes.py
backendcrew/api/runs.py
backendcrew/api/schedules.py
backendcrew/api/task_statuses.py
backendcrew/api/tasks.py
backendcrew/api/tools.py
backendcrew/api/uc_tools.py
backendcrew/api/upload.py
backendcrew/callbacks/__init__.py
backendcrew/callbacks/base.py
backendcrew/callbacks/logging_callbacks.py
backendcrew/callbacks/storage_callbacks.py
backendcrew/callbacks/streaming_callbacks.py
backendcrew/callbacks/transformation_callbacks.py
backendcrew/callbacks/validation_callbacks.py
backendcrew/static/build/asset-manifest.json
backendcrew/static/build/favicon.ico
backendcrew/static/build/favicon.png
backendcrew/static/build/index.html
backendcrew/static/build/logo192.png
backendcrew/static/build/logo512.png
backendcrew/static/build/manifest.json
backendcrew/static/build/robots.txt
backendcrew/static/build/static/css/main.616ba065.css
backendcrew/static/build/static/css/main.616ba065.css.map
backendcrew/static/build/static/js/213.042bb37f.chunk.js
backendcrew/static/build/static/js/213.042bb37f.chunk.js.LICENSE.txt
backendcrew/static/build/static/js/213.042bb37f.chunk.js.map
backendcrew/static/build/static/js/239.dfdb0d71.chunk.js
kasal-0.0.0.1.dist-info/licenses/LICENSE
kasal-0.0.0.1.dist-info/METADATA
kasal-0.0.0.1.dist-info/WHEEL
kasal-0.0.0.1.dist-info/entry_points.txt
kasal-0.0.0.1.dist-info/top_level.txt
kasal-0.0.0.1.dist-info/RECORD
