Metadata-Version: 2.4
Name: kasal
Version: 0.0.0.1
Summary: A modern web application with AI capabilities
Author-email: Nehme Tohme <nehmetohme@gmail.com>
License: MIT License
Project-URL: Homepage, https://github.com/yourusername/kasal
Project-URL: Documentation, https://github.com/yourusername/kasal/docs
Project-URL: Repository, https://github.com/yourusername/kasal.git
Project-URL: Issues, https://github.com/yourusername/kasal/issues
Keywords: databricks,ai,web-interface,fastapi,react
Classifier: Development Status :: 3 - Alpha
Classifier: Intended Audience :: Developers
Classifier: License :: OSI Approved :: MIT License
Classifier: Programming Language :: Python :: 3
Classifier: Programming Language :: Python :: 3.10
Classifier: Programming Language :: Python :: 3.11
Classifier: Programming Language :: Python :: 3.12
Classifier: Programming Language :: Python :: 3.13
Classifier: Topic :: Software Development :: Libraries :: Python Modules
Requires-Python: <=3.13,>=3.10
License-File: LICENSE
Requires-Dist: google-api-python-client
Requires-Dist: databricks
Requires-Dist: databricks.sdk
Requires-Dist: crewai-tools
Requires-Dist: youtube-transcript-api
Requires-Dist: aiosqlite>=0.19.0
Requires-Dist: sqlalchemy[asyncio]>=2.0.0
Requires-Dist: aiohttp>=3.9.0
Requires-Dist: python-dotenv>=1.0.0
Requires-Dist: croniter==2.0.1
Requires-Dist: weaviate-client
Requires-Dist: pysendpulse
Requires-Dist: snowflake
Requires-Dist: snowflake-connector-python
Requires-Dist: cryptography<44.0.0
Requires-Dist: flask==3.0.0
Requires-Dist: flask_cors
Requires-Dist: crewai[tools]
Requires-Dist: psutil
Requires-Dist: requests>=2.31.0
Requires-Dist: fastapi
Requires-Dist: browser-use
Requires-Dist: pytest-asyncio
Requires-Dist: pytest-cov
Requires-Dist: litellm
Requires-Dist: baml-py
Requires-Dist: python-multipart
Dynamic: license-file
